{
"type": "FeatureCollection",
"name": "road_network",
"crs": { "type": "name", "properties": { "name": "urn:ogc:def:crs:EPSG::25832" } },
"features": [
{ "type": "Feature", "properties": { "fid": 1, "truck_traffic_daily": 960, "eisenbahn": 0, "anlieger": 0, "hauptverk": 0, "car_traffic_daily": 10810, "max_speed": 50, "hauptsaml": 1, "id": 1000, "name": "hauptsammelstrasse", "str_stairs": "false" }, "geometry": { "type": "LineString", "coordinates": [ [ 567564.0, 5931765.0 ], [ 567506.027313499827869, 5931808.769077715463936 ] ] } },
{ "type": "Feature", "properties": { "fid": 2, "truck_traffic_daily": 410, "eisenbahn": 0, "anlieger": 0, "hauptverk": 0, "car_traffic_daily": 6580, "max_speed": 50, "hauptsaml": 1, "id": 1001, "name": "hauptsammelstrasse", "str_stairs": "false" }, "geometry": { "type": "LineString", "coordinates": [ [ 567506.027313499827869, 5931808.769077715463936 ], [ 567562.492097680573352, 5931920.636136697605252 ], [ 567497.071877299109474, 5931953.573927468620241 ] ] } },
{ "type": "Feature", "properties": { "fid": 3, "truck_traffic_daily": 270, "eisenbahn": 0, "anlieger": 0, "hauptverk": 0, "car_traffic_daily": 4400, "max_speed": 50, "hauptsaml": 1, "id": 1002, "name": "hauptsammelstrasse", "str_stairs": "false" }, "geometry": { "type": "LineString", "coordinates": [ [ 567497.071877299109474, 5931953.573927468620241 ], [ 567423.455155988223851, 5931993.190348627977073 ], [ 567350.445582894259132, 5932028.101371105760336 ] ] } },
{ "type": "Feature", "properties": { "fid": 4, "truck_traffic_daily": 40, "eisenbahn": 0, "anlieger": 0, "hauptverk": 0, "car_traffic_daily": 605, "max_speed": 50, "hauptsaml": 1, "id": 1004, "name": "hauptsammelstrasse", "str_stairs": "false" }, "geometry": { "type": "LineString", "coordinates": [ [ 567350.445582894259132, 5932028.101371105760336 ], [ 567305.668401890667155, 5932053.449809164740145 ], [ 567258.917989182053134, 5932071.816042728722095 ], [ 567187.426286630681716, 5932099.137712493538857 ], [ 567176.49761872459203, 5932102.173453580588102 ], [ 567158.586746323155239, 5932109.914593347348273 ], [ 567142.193744464311749, 5932116.896797842346132 ], [ 567088.393001858959906, 5932130.69642589148134 ], [ 567065.085920905694366, 5932136.477327840402722 ], [ 567046.112539124442264, 5932142.245235902257264 ], [ 567021.674823390319943, 5932148.468505126424134 ], [ 566974.317262464552186, 5932160.763256520964205 ] ] } },
{ "type": "Feature", "properties": { "fid": 5, "truck_traffic_daily": 85, "eisenbahn": 0, "anlieger": 0, "hauptverk": 0, "car_traffic_daily": 1050, "max_speed": 50, "hauptsaml": 1, "id": 1005, "name": "hauptsammelstrasse", "str_stairs": "false" }, "geometry": { "type": "LineString", "coordinates": [ [ 566974.317262464552186, 5932160.763256520964205 ], [ 566916.0, 5932170.0 ], [ 566904.0, 5932173.0 ], [ 566890.986169681651518, 5932175.031239619478583 ], [ 566787.012037520878948, 5932186.718842796981335 ], [ 566754.0, 5932146.0 ], [ 566691.0, 5932053.0 ], [ 566681.823608926148154, 5932039.333613120950758 ] ] } },
{ "type": "Feature", "properties": { "fid": 6, "truck_traffic_daily": 45, "eisenbahn": 0, "anlieger": 0, "hauptverk": 0, "car_traffic_daily": 445, "max_speed": 50, "hauptsaml": 1, "id": 1006, "name": "hauptsammelstrasse", "str_stairs": "false" }, "geometry": { "type": "LineString", "coordinates": [ [ 566681.823608926148154, 5932039.333613120950758 ], [ 566899.334457665216178, 5931884.359030734747648 ] ] } },
{ "type": "Feature", "properties": { "fid": 7, "truck_traffic_daily": 210, "eisenbahn": 0, "anlieger": 0, "hauptverk": 0, "car_traffic_daily": 1365, "max_speed": 50, "hauptsaml": 1, "id": 1007, "name": "hauptsammelstrasse", "str_stairs": "false" }, "geometry": { "type": "LineString", "coordinates": [ [ 566899.334457665216178, 5931884.359030734747648 ], [ 567151.300967718940228, 5931719.214715712703764 ], [ 567080.264626330230385, 5931604.767276808619499 ], [ 567159.0, 5931552.0 ] ] } },
{ "type": "Feature", "properties": { "fid": 8, "truck_traffic_daily": 1560, "eisenbahn": 0, "anlieger": 0, "hauptverk": 0, "car_traffic_daily": 3315, "max_speed": 50, "hauptsaml": 1, "id": 1008, "name": "hauptsammelstrasse", "str_stairs": "false" }, "geometry": { "type": "LineString", "coordinates": [ [ 567159.0, 5931552.0 ], [ 567021.0, 5931291.0 ], [ 567000.0, 5931282.0 ], [ 566991.0, 5931279.0 ], [ 566973.0, 5931270.0 ], [ 566961.0, 5931228.0 ] ] } },
{ "type": "Feature", "properties": { "fid": 9, "truck_traffic_daily": 765, "eisenbahn": 0, "anlieger": 0, "hauptverk": 0, "car_traffic_daily": 1665, "max_speed": 50, "hauptsaml": 1, "id": 1009, "name": "hauptsammelstrasse", "str_stairs": "false" }, "geometry": { "type": "LineString", "coordinates": [ [ 566961.0, 5931228.0 ], [ 566955.0, 5931207.0 ], [ 566943.0, 5931168.0 ], [ 566931.0, 5931123.0 ], [ 566916.0, 5931072.0 ], [ 566838.0, 5930970.0 ] ] } },
{ "type": "Feature", "properties": { "fid": 10, "truck_traffic_daily": 1720, "eisenbahn": 0, "anlieger": 0, "hauptverk": 0, "car_traffic_daily": 4660, "max_speed": 50, "hauptsaml": 1, "id": 1011, "name": "hauptsammelstrasse", "str_stairs": "false" }, "geometry": { "type": "LineString", "coordinates": [ [ 567399.0, 5931426.0 ], [ 567186.0, 5931540.0 ], [ 567159.0, 5931552.0 ] ] } },
{ "type": "Feature", "properties": { "fid": 11, "truck_traffic_daily": 960, "eisenbahn": 0, "anlieger": 0, "hauptverk": 1, "car_traffic_daily": 11770, "max_speed": 60, "hauptsaml": 0, "id": 1, "name": "hauptverkehrsstrasse", "str_stairs": null }, "geometry": { "type": "LineString", "coordinates": [ [ 567827.851164953201078, 5932218.639718377031386 ], [ 567480.219482513610274, 5931578.500350805930793 ] ] } },
{ "type": "Feature", "properties": { "fid": 12, "truck_traffic_daily": 790, "eisenbahn": 0, "anlieger": 0, "hauptverk": 1, "car_traffic_daily": 2615, "max_speed": 60, "hauptsaml": 0, "id": 2, "name": "hauptverkehrsstrasse", "str_stairs": null }, "geometry": { "type": "LineString", "coordinates": [ [ 566835.65383940259926, 5930970.166248614899814 ], [ 565585.078564300085418, 5931274.765620922669768 ] ] } },
{ "type": "Feature", "properties": { "fid": 13, "truck_traffic_daily": 790, "eisenbahn": 0, "anlieger": 0, "hauptverk": 1, "car_traffic_daily": 2615, "max_speed": 60, "hauptsaml": 0, "id": 3, "name": "hauptverkehrsstrasse", "str_stairs": null }, "geometry": { "type": "LineString", "coordinates": [ [ 567105.252283695386723, 5930960.35598000138998 ], [ 567062.025787623366341, 5930940.490186063572764 ], [ 567007.333540111547336, 5930932.64197117369622 ], [ 566947.00038814812433, 5930942.20698307082057 ], [ 566840.068460277980193, 5930967.713681461289525 ], [ 566836.307857310050167, 5930970.166248614899814 ] ] } },
{ "type": "Feature", "properties": { "fid": 14, "truck_traffic_daily": 2040, "eisenbahn": 0, "anlieger": 0, "hauptverk": 1, "car_traffic_daily": 9125, "max_speed": 60, "hauptsaml": 0, "id": 4, "name": "hauptverkehrsstrasse", "str_stairs": null }, "geometry": { "type": "LineString", "coordinates": [ [ 567480.219482513610274, 5931578.500350805930793 ], [ 567290.686798517359421, 5931204.795172914862633 ], [ 567260.274965820484795, 5931149.775916449725628 ], [ 567243.270500226528384, 5931120.672119568102062 ], [ 567234.768267429550178, 5931093.85738536156714 ], [ 567181.792816925561056, 5931016.601520042866468 ], [ 567147.129867830197327, 5930986.516696299426258 ], [ 567107.214337417739443, 5930961.337006863206625 ], [ 567105.313597873551771, 5930960.417294181883335 ] ] } }
]
}
